display_nb.py
nbimporter.py
nbimporter-0.3.4.dist-info/LICENSE
nbimporter-0.3.4.dist-info/METADATA
nbimporter-0.3.4.dist-info/WHEEL
nbimporter-0.3.4.dist-info/top_level.txt
nbimporter-0.3.4.dist-info/RECORD
